survivalvolume/__init__.py
survivalvolume/parse.py
survivalvolume/plot.py
survivalvolume-1.2.4.dist-info/LICENSE
survivalvolume-1.2.4.dist-info/METADATA
survivalvolume-1.2.4.dist-info/WHEEL
survivalvolume-1.2.4.dist-info/top_level.txt
survivalvolume-1.2.4.dist-info/zip-safe
survivalvolume-1.2.4.dist-info/RECORD
